seff/__init__.py
seff/seff.py
seff/setup.py
seff/support.py
seff-1.0.dist-info/METADATA
seff-1.0.dist-info/WHEEL
seff-1.0.dist-info/top_level.txt
seff-1.0.dist-info/RECORD
