Metadata-Version: 2.1
Name: seff
Version: 1.0
Summary: A compact and efficient binary file serializer and deserializer for Python dictionaries.
Home-page: https://github.com/zugebot/seff
Author: Jerrin Shirks
Author-email: jerrinshirks@gmail.com
License: UNKNOWN
Platform: UNKNOWN
